etsi/watchdog/__init__.py
etsi/watchdog/cli.py
etsi/watchdog/compare.py
etsi/watchdog/config.py
etsi/watchdog/drift_check.py
etsi/watchdog/hooks.py
etsi/watchdog/logger.py
etsi/watchdog/monitor.py
etsi/watchdog/slack_notifier.py
etsi/watchdog/utils.py
etsi/watchdog/drift/__init__.py
etsi/watchdog/drift/base.py
etsi/watchdog/drift/factory.py
etsi/watchdog/drift/ks.py
etsi/watchdog/drift/psi.py
etsi/watchdog/drift/shap_drift.py
etsi/watchdog/drift/sklearn_wrapper.py
etsi/watchdog/drift/wasserstein.py
etsi/watchdog/models/__init__.py
etsi/watchdog/models/isolation_forest.py
etsi/watchdog/report/generate.py
etsi_watchdog-3.0.0.dist-info/licenses/LICENSE
etsi_watchdog-3.0.0.dist-info/METADATA
etsi_watchdog-3.0.0.dist-info/WHEEL
etsi_watchdog-3.0.0.dist-info/top_level.txt
etsi_watchdog-3.0.0.dist-info/RECORD
