Metadata-Version: 2.4
Name: etsi-watchdog
Version: 3.0.0
Summary: Real-time data drift detection for machine learning pipelines.
Author-email: Etsi <etsi.hq@gmail.com>
License: BSD-2-Clause
Requires-Python: >=3.8
License-File: LICENSE
Requires-Dist: pandas>=1.0.0
Requires-Dist: numpy
Requires-Dist: scipy
Requires-Dist: slack_sdk
Requires-Dist: scikit-learn
Requires-Dist: jinja2
Requires-Dist: matplotlib
Requires-Dist: seaborn
Dynamic: license-file
